quickvec/__init__.py
quickvec/convert.py
quickvec/embedding.py
quickvec/py.typed
quickvec/show.py
quickvec-0.3.0.dist-info/LICENSE
quickvec-0.3.0.dist-info/METADATA
quickvec-0.3.0.dist-info/WHEEL
quickvec-0.3.0.dist-info/entry_points.txt
quickvec-0.3.0.dist-info/top_level.txt
quickvec-0.3.0.dist-info/RECORD
